{"14":1,"16":1,"17":4,"18":3,"19":3,"21":2,"23":3,"25":1,"26":2,"27":1,"30":2,"31":1,"mid-October":5,"autumn":15,"Friday":291,"summer":115,"next week 's annual":1,"Tuesday":311,"late January":9,"Saturday":224,"this year":117,"December":221,"the last year":14,"winter":27,"Monday":253,"Aug":48,"July":191,"11 p.m.":10,"the past":161,"more than 12 years":2,"the 1970s":54,"May":200,"end of two months":1,"fall":86,"the year":76,"a few minutes":12,"the 1950s":13,"January":257,"last summer":24,"1960s":12,"August":199,"Years":2,"nearly a week":4,"the first quarter":54,"December last year":6,"Sunday 28":3,"today may":1,"last week":161,"this week":102,"Wednesday":274,"the 1930s":30,"the":170,"the month":13,"the day":75,"Friday 19":2,"once":102,"one day":4,"a":47,"the 22nd minute":1,"June":243,"now":246,"nearly a decade":2,"Christmas":111,"last December":10,"fall yesterday":2,"1969 to":1,"today":150,"the weekend":81,"Wednesday 15":1,"the second and third quarters":1,"months":40,"eight minutes":6,"February":208,"a year":25,"earlier":10,"the start of the Millennium":2,"this":63,"last year":226,"time":293,"next year":46,"recently":54,"morning":20,"late February":3,"past":71,"two-month":4,"decades":14,"52 weeks":2,"more than two years in":1,"the 1920s":14,"Sunday":231,"last month":98,"March":234,"the past week":9,"yesterday":104,"the coming months":24,"the second quarter":65,"first year":10,"three-year":6,"this spring":8,"three years":24,"ten minute":2,"Saturday 19":1,"the future":114,"56 minutes":4,"this past spring":1,"a few months":6,"late 1990s":7,"next month":34,"the 1880s":3,"first week":5,"the last":13,"last August":6,"day of the":2,"2005 before":2,"Sept":83,"the 1990s":58,"the 20th century":5,"Every Day":1,"November":187,"the sixth minute":2,"this month":31,"2005 and 2008":5,"afternoon":16,"last 19":1,"two hours":10,"current":99,"the week":51,"last winter":1,"present":43,"Jan":42,"August last year":3,"first-half":3,"March of last year":1,"57-year-old":2,"seven months":4,"80-minutes":2,"September":246,"the third quarter last year":1,"the next":5,"later this month":2,"October":182,"the next year":8,"the final three months of":7,"mid-December":4,"last":150,"the near future":19,"a row in August":1,"the end of the year":28,"the 20th Century":2,"11 years":8,"seven-month":6,"55 minutes":4,"the third quarter":73,"1100 and 1700":2,"the 7th century":1,"right now":21,"the past month":11,"Nov":38,"last Friday":6,"four-month":4,"39-year-old":2,"Tuesday 18":2,"the past year":38,"less than a year":4,"the last week of October":1,"the first fiscal quarter ended":1,"July summer":1,"April":184,"September , the twelfth month":1,"previously":28,"last October":17,"six":7,"the following week":3,"the second":31,"late November":10,"the first quarter of fiscal":2,"the fourth quarter":60,"late":13,"the 1980s":68,"January 24th , 2010":2,"Easter":21,"0030 and 0139":2,"the previous year":4,"98th year":1,"weekend":34,"84-79":1,"the 21st Century":4,"last recession seven years":2,"July 25 of last season":2,"early January":8,"eight weeks ago":1,"the end":12,"Thursday":239,"last two months":2,"first day":3,"New Year 's":5,"tonight":21,"the decade":5,"the late 1990s before":1,"the coming two":1,"three months":12,"9 pm":4,"1970s":26,"1996 one quarter":1,"March last year":6,"the first three months of":10,"the 1960s":39,"a day":14,"less than a week on":1,"the prior year":10,"the late":2,"early 2007 may now":1,"New Year":12,"February last year":5,"the last minute":10,"last two years":5,"late summer":3,"last weekend":17,"week":22,"Monday 23":1,"this day":6,"13-year-old":4,"Sats":1,"Feb":33,"next":21,"the coming days":26,"the late ' 80s":2,"three-day":2,"six days":2,"late on Thursday":1,"the early hours of Friday":2,"several weeks ago":5,"earlier yesterday":1,"Dec":46,"tomorrow":19,"late December":7,"next four years":1,"September last year":8,"fiscal first quarter":2,"future":70,"new year":13,"the last financial year":2,"the beginning of the year":9,"3 p.m.":2,"the next fortnight":1,"tuesday":1,"a second":18,"the middle":1,"Monday 22":4,"90 minutes":10,"the first four months of":1,"13,000 years ago":2,"evening":6,"the 79th minute":3,"late July":7,"the first quarter of this":2,"24 years":4,"the first six months of":6,"dinnertime":2,"last Thursday":5,"next week":40,"the coming weeks":12,"Jul":1,"midnight":38,"early":19,"mid-March":2,"March this year":1,"the third quarters":1,"the coming year":6,"the start of":2,"night":76,"the hour":7,"the end of July":9,"nearly three decades":2,"Tuesday ,":2,"next two days":1,"spring":52,"seconds later":1,"this morning":4,"the start of this year":9,"26-year-old":4,"early Wednesday":2,"20-30":2,"the coming years":6,"a week ago":2,"the 1940s":8,"1862 and 1918":2,"Monday 13":5,"the early 1980s":7,"Tuesday 19":2,"a month":7,"at least":2,"nearly 40 years ago":1,"19th century":1,"Saturday Oct":3,"24 weeks":2,"the 17th century":5,"this summer":19,"mid-September":15,"19th-century":1,"late spring":2,"yesterday afternoon":3,"more than a century":2,"late March":3,"the last week":6,"the middle of the day":1,"the end of the third":3,"2006 and 2010":2,"1969 to 1970":1,"next summer":3,"the early":10,"the 16th century":6,"over three years":2,"second-quarter":9,"this decade":4,"first months":1,"early September":7,"a year earlier":3,"three minutes":4,"september":1,"the quarter":40,"late April":14,"the ' 90s":2,"later this":6,"the three months from June":1,"10 minutes":4,"the end of June":7,"seven":3,"earlier this year":7,"more than seven hours":2,"now and April":2,"currently":22,"and 19th minutes":1,"year-end":2,"dawn Tuesday":2,"second half this season":1,"the end of the month":13,"two months this week":1,"27th":2,"the fourth quarter this year":1,"the last month":6,"last 27":1,"four hours":2,"the eleventh hour":2,"18-minute":2,"13th inning Friday":1,"the following April":1,"Tuesday 24":3,"two weeks":11,"the past decade":9,"early February":11,"two-year":8,"16 years":4,"the Year":1,"1998 and 2003":3,"two months":5,"Thursday 15":1,"5 p.m.":6,"the month before":1,"the start of last week":1,"fourth-quarter":10,"December quarter":1,"eight years":14,"Saturday November":2,"eight-month":2,"the next week":1,"third-quarter":9,"Wednesday next":1,"the beginning of March":4,"9 a.m.":10,"weeks":16,"the 21st century":7,"the 2007 fourth quarter":1,"Friday 20":3,"May or June":1,"Thursday 20":3,"overnight":10,"last week 's two-day":2,"the next month":1,"hours":14,"Once":1,"Thanksgiving":20,"13 months":1,"early March":8,"early Sunday":2,"the end of last year":17,"years":87,"75 years":2,"Today":4,"nearly an hour":2,"more than a decade":1,"last June":5,"the first nine months of":6,"nine years":4,"the end of the first":3,"the three months that ended":2,"1 p.m.":4,"two years later":6,"last February":5,"Tuesday 25":1,"Oct":23,"April and June":4,"about 2 hours":2,"the early 1940s":1,"three weeks":6,"14 years":6,"second half":3,"2005 and 2011":2,"days":14,"Test last weekend":1,"1983 before":1,"the second half of the":3,"first half of fiscal":1,"January and March":8,"weeks this year":1,"ten years":6,"one to five years":2,"This year":1,"a few":9,"three":7,"the April-June second quarter":1,"dawn Wednesday":6,"Bochum":3,"the prior fiscal year quarter":1,"earlier this month":9,"2009 Winter":1,"this weekend":16,"the month of":1,"the eighth minute":2,"1996 and 2007":2,"Wednesday before":2,"two years from":1,"Thursday second":1,"13th year":1,"the beginning of next year":1,"Thursday 19":4,"1 December last year":2,"the current":1,"Yesterday":2,"this Saturday":1,"5 a.m.":2,"last two":2,"1920s":1,"nights":4,"two years ago":7,"April of last year":1,"the 1400s":2,"the second half":11,"1990s":5,"11 a.m.":4,"two weeks later":1,"Christmas Day aged":1,"five weeks":6,"1590 and 1662":2,"last 18 months":2,"the late ' 70s":2,"late August":9,"midnight on":8,"16th-century":2,"a month on Monday":1,"the 37th minute":1,"wed":3,"17-year-old":2,"the mid-1950s":4,"2003 and 2007":8,"last minute":2,"Monday 29":3,"last Sunday":10,"the month of September":1,"January this year":1,"midnight last night":2,"24-24":1,"December last":2,"last fall":20,"33-year":2,"16-year-old":2,"Thursday 14":3,"first-quarter":11,"noon":15,"a couple":1,"one-day":4,"2003 and 2006":3,"Thursday 27":1,"1996 and 1999":2,"12-hour":2,"more than 20 hours":2,"early on Wednesday":1,"nearly two years ago":1,"the 76th minute":1,"the second half of March":1,"the current year":1,"the 16th minute":1,"28-year-old":2,"late yesterday":1,"21-year-old":4,"Thursday 23":1,"first":3,"next month 's autumn":1,"the beginning of the decade":1,"last May":5,"7 a.m.":4,"two weeks ago":3,"Tuesday 21":2,"1 Day":1,"March a fourth-quarter":1,"a decade":19,"a year ago":5,"about 10 years":2,"year":31,"30 minutes":2,"97-87":1,"the early 20th century":3,"the Islamic":2,"89-year-old":2,"2004 and 2006":2,"1997 and 2001":2,"25-year":2,"the ' 80s":3,"January fall":2,"a few weeks":4,"the start of the year":19,"Tonight":4,"last November":14,"the next decade":3,"Sunday Nov":1,"the late 20th century":1,"last four years":3,"ten minutes":2,"last July":10,"five years":13,"25 minutes":2,"38 years":2,"the first 19 days of":1,"the 66th minute":2,"early Friday":3,"the three":1,"the mid-1990s":15,"Thursday 28":1,"100th birthday":1,"a few years":3,"72-hour":2,"2004 and 2008":2,"nearly eight":1,"2007 once":1,"the following":6,"a week":26,"June this year":1,"last Saturday":4,"the mid-20th century":3,"the last four months of":1,"Thursday 17":1,"next January":6,"previous years":7,"the other day":1,"end of the first":2,"October last year":3,"second week":2,"last spring":4,"last three years to":1,"the sixth straight":1,"32nd year":1,"the 2002 third quarter":2,"the last decade":5,"last 12 years":1,"the early 1990s":23,"the previous month":1,"the beginning of the first":1,"Monday , August":1,"late last month":5,"Winter":6,"early on Saturday":3,"the first half":8,"the first half of next":2,"Wednesday 29":4,"25 years":2,"1992 and 1996":2,"two years":25,"last 24 hours":1,"march Saturday":1,"five years ago":1,"1990 and 2000":2,"2006 before":1,"march":7,"12-year":4,"Thursday 31":1,"May of this year":1,"November last year":6,"May last year":3,"the minute":2,"later this year":7,"this hour":2,"the 21st":2,"December 12th":2,"Thursday 16":3,"1980s":6,"beginning October":1,"41 seconds":2,"previous weeks":1,"Tuesday 29":5,"18-year-old":4,"Tuesday 15":2,"the coming":2,"the previous":2,"1982 , 1987":2,"the 62nd minute":1,"previous quarters":1,"2005-2009":2,"the previous quarter":3,"the 57th minute":3,"the night before":2,"late last week":3,"the second quarter of the":2,"early next month":1,"April and October last year":2,"Sunday 13":4,"the start of the second":7,"wounding":1,"1946 and":1,"a couple of years":4,"early morning":4,"November and December":2,"3 hours":2,"12-year-old":2,"13 years":4,"next years":1,"two":16,"last April":1,"five-year":8,"last night":11,"earlier this week":12,"last two years ended":1,"September and November last year":2,"6 years old":2,"late October":5,"the 21st minute":2,"six years":12,"20 weeks":2,"the end of this year":10,"a day earlier":4,"49 minutes":2,"late 1980s":1,"yesterday 's minutes":2,"22-year-old":4,"the coming quarters":1,"a week later":2,"more than a week":2,"the second half of this":3,"early July":6,"12 weeks":2,"2003 and 2008":4,"the first 14 minutes of":1,"the three months to the":1,"0230 and 0330":2,"20-year-old":4,"July last":1,"seven years":14,"the Millennium":2,"2002 and 2005":2,"95th Congress of 1977-1979":1,"8 a.m. and 11 p.m.":2,"eight weeks":2,"more than a year":5,"June last year":3,"six months":8,"last March":6,"15 month":2,"18 years":4,"may":2,"the fourth quarter last year":2,"the fourth quarter a year":2,"1988 to":1,"40 years":8,"19-year-old":2,"early next year":3,"early May":5,"the 23rd minute":1,"more":10,"27 minutes":4,"15-year-old":6,"next Sunday":1,"the 43rd minute":3,"third week":2,"next Monday":2,"late Wednesday":4,"nearly seven years":2,"day":44,"last 10 minutes":1,"beginning":4,"the same quarter":1,"10 a.m.":2,"the last quarter":3,"the fiscal first quarter":1,"the end of this week":1,"100 years ago":2,"September and April":2,"second year now":1,"the end of":11,"Summer":11,"20 years old":2,"Monday 19":1,"Monday , March":1,"1989 and 2004":2,"sixth week":1,"1700 and 2300":2,"2 pm":2,"March-April this year":1,"the previous week":1,"second":3,"early fall":2,"a year this month":1,"the 18th century":2,"early on Tuesday":1,"two months ago":2,"this last week":1,"near":1,"Tuesday 30":2,"6-year-old":2,"Now":7,"four":5,"Last year":1,"1931 , the second":1,"the second year":3,"25 days":2,"the 68th minute":1,"the first":6,"' 60s":1,"the years 2015 , 2050":1,"several":4,"the end of January":9,"early August":2,"14-year":2,"the first year":3,"late last year":4,"now and Friday":2,"19-9 1":1,"1930s":2,"Christmas Day":3,"the 19th century":9,"the 82nd minute":1,"the same quarter a year":2,"three days":6,"the next fiscal year":1,"00 pm":8,"1995-96":1,"2005 and 2006":4,"the third year":1,"the end of this month":2,"2005 took 15 days":1,"Wednesday 26":2,"ten days":2,"50 years":6,"several months":6,"Friday , March":1,"April and July":2,"this past weekend":1,"five-year-olds":2,"the coming decades":2,"the first month":1,"' 16":1,"12th-century":1,"the end of September":4,"the 19th-century":1,"2005 and 2007":11,"two decades":2,"several days":8,"last season":2,"Monday , Sept":1,"five days":4,"24th year":1,"the ninth century":3,"24-hour":4,"about four months ago":1,"two-year-old":2,"a century":4,"22 years":6,"past two years":1,"several years ago":1,"the Easter":2,"thanksgiving":2,"Tuesday 16":2,"six months to 30":1,"about a":2,"early last":2,"the early morning hours of":1,"65 minutes":2,"1980 and 2005":2,"February this year":2,"29 minutes":2,"the beginning of the month":3,"earlier this":25,"the 70th minute":1,"2012 and 2017":2,"Thursday 24":3,"an hour":7,"September 11 attacks of":1,"one year":7,"Wednesday 13":2,"Wednesday Nov":1,"nearly 14 months":2,"four years":14,"eight minutes of first-quarter":1,"2000 and 2009":2,"five-year-old":2,"last 11 minutes of":1,"medieval":3,"later Saturday":1,"the start":2,"the early hours of Saturday":4,"Halloween":7,"21st-century":3,"12 months":5,"1 pm":2,"last few":1,"last Tuesday":1,"Wednesday 16":2,"1968 and 1970":1,"the 77th minute":3,"two-minute":2,"the 9th of January":2,"six-month":12,"the mid ' 80s":2,"late September":8,"last Wednesday":5,"this winter":5,"Thursday 26":2,"last year 's second half":1,"Saturday 21":2,"the end of last week":2,"Wednesdays":1,"years end in":2,"the early 1960s":1,"the full":1,"Friday 18":1,"this past summer":1,"the final minutes of Friday":1,"next 12 years":1,"60-year-old":2,"the rear quarter":1,"October and February":4,"second year":3,"five months ago":2,"7 p.m.":4,"the mid-1980s":2,"the early ' 90s":2,"the 1890s":2,"a row in July":1,"about three hours":2,"0800 and 0930":2,"nearly":6,"18th-century":1,"the first 4 minutes of":1,"2002 and 2006":2,"Thursday in":2,"the final quarter of last":2,"Monday November":1,"1917 before":1,"the end of World War":2,"the fiscal year":3,"the early 20th":1,"two days":14,"the fourth minute":3,"1991 and 2001":2,"the early 1950s":2,"18th year":1,"84-76":1,"15 years ago":1,"later":5,"1 a.m.":4,"the 13th century":1,"April and June this year":2,"the middle of the last":2,"the mid-1970s":7,"previous years before":1,"last September":7,"eleventh hour":2,"the big day":6,"Thursday October":1,"500 years":2,"14 days later":1,"more than":6,"the fourth quarter of last":1,"the 61st minute":1,"St. Patrick 's Day":1,"May of":1,"the mid-19th Century":1,"a couple of weeks":1,"eight":3,"' 30s":1,"the three months ended Oct":1,"sunrise Sunday":1,"the ' 70s":4,"last day":2,"2000 and 2003":2,"the beginning of this year":4,"past 30 years":1,"the Jan":2,"1993 when 18":2,"£ 18":2,"12 years":6,"20 July and 20 September":2,"35th year":1,"the end of the day":8,"February next year":2,"1962-63":1,"April and June last year":2,"early 20th Century":1,"the third minute":1,"the first two months of":3,"16 and 18 October 2008":2,"86-year-old":4,"Sunday 21":2,"late last fall":1,"Wednesday 24":3,"second weekend":2,"98-88":1,"March 22nd":1,"1987 and last year":2,"this afternoon":5,"more than 150 years":2,"more than 15 hours":2,"two months old":2,"lunchtime":10,"the new fiscal year":1,"nearly 16":2,"60 Minutes":2,"last four":1,"the end of last month":1,"the sixteenth century":1,"Wednesday 22":2,"2006 and last year":2,"last six years":1,"fourth quarter":2,"2-year-old":2,"this fall":7,"six-day":4,"one year may":1,"15-month":4,"the early 16th century":1,"the winter":2,"the year-ago quarter":2,"Monday 's":1,"the tenth minute":1,"the first half of this":1,"Night":2,"Election Day on Nov":2,"back-and-forth second quarter":1,"nearly four decades":2,"the start of the day":2,"1955 and 1966":2,"3 years":2,"the start of August":2,"the early hours of Sunday":4,"Columbus Day":1,"the 1830s":1,"the late 1970s":1,"three years ago":4,"spring before":1,"' 70s":1,"the same week":2,"18 months":12,"the beginning of the week":1,"2002 and 2008":2,"next spring":3,"the first quarter Monday":1,"the first half of the":3,"midnight on 26":2,"hours of the day":2,"2018 / 19":1,"Friday 17":1,"the start of the new":1,"two years in December":1,"next April":3,"this lunchtime":2,"46-year-old":4,"one quarter":5,"the end of this":1,"the early fourth quarter":1,"23-year-old":2,"St. Patrick 's":1,"Tuesday 28":2,"the third quarter Sunday":1,"the 27th minute":2,"months on Monday":1,"1991 to 2002":1,"1830 and 1945":2,"2010-2012":2,"2010 , last month":1,"the past three days may":1,"late 1960s":1,"ten":1,"33 years":2,"yesterday before":1,"mid-January":1,"Friday 14":2,"36 years":2,"last Christmas":1,"1955-56":2,"1950s":1,"last month escaped Wednesday":1,"1977 and 1988":2,"a decade ago":1,"Monday 27":2,"the start of next year":1,"24 hours":2,"1999-2000":4,"1981-82":3,"five":6,"12 years old":4,"August 27th":1,"0.030 seconds":2,"23-month-old":2,"the second minute of the":1,"Future":1,"January-September":1,"1984 and 2006":2,"11th inning":1,"four days ago":1,"the fourth day":1,"14 weeks":2,"first weekend":1,"the 3rd quarter of 2006":1,"stimulus-driven second":2,"Wednesday 23":1,"27-year-old":2,"15-30":1,"May 1st":1,"next fall":1,"the night":4,"April last year":2,"Saturday 15":1,"10 am":2,"August 11th":1,"Sunday 31":1,"mid July":1,"the 2012 Summer":1,"1997 to":1,"the spring of this year":1,"fourth week":1,"several years":6,"the 10th minute":1,"the bottom quarter":1,"the early ' 80s":1,"mid-November":6,"1935 and":1,"20 a.m.":4,"Thursday 30":1,"20 years ago":1,"august 13th":1,"five months":4,"the mid-1960s":2,"about the beginning of the":1,"Monday 16":1,"now and the end of":2,"99 years":2,"a few weeks ago":1,"Monday 24":1,"end of June":1,"two days later":3,"second half of the":3,"eight-year-old":2,"early this year":2,"the end of the Second":4,"three weeks ago":4,"31-year":2,"the last three months of":2,"8 p.m. local time":2,"14-year-old":4,"October and March":2,"Sunday 26":2,"returning four years later":2,"1970 aged 27":1,"Doomsday":2,"past three months":1,"last more":1,"two-week":4,"July this year":2,"one-day fall":1,"more than a":1,"the fourth calendar quarter of":1,"8 years later":2,"four days later":2,"1950-53":1,"the fifth month":1,"early Tuesday":4,"the year before":4,"six years this week":1,"end of Q1 2007":1,"November-December":2,"the past financial year":1,"the early hours of Monday":1,"-":2,"last two decades":1,"this Thanksgiving":1,"Friday 24":3,"Friday 27":1,"6 a.m.":2,"the earnest years":2,"the first 10 months of":1,"late Thursday":6,"about lunchtime":1,"and 16th centuries":2,"1937 and 2006":2,"the end of next week":3,"four-year":2,"the middle of the second":2,"the 91st minute":1,"the fourth":5,"February this":2,"last couple of years":1,"last Monday":1,"the prior":1,"fall of apartheid 15":2,"the 1976 Winter":1,"the next day":6,"late this":1,"the ninth":1,"10 p.m. at night":2,"the same year":3,"The Millennium":2,"the second quarter of this":2,"the April-June quarter":3,"the three months from July":2,"29-20":1,"last three days":1,"sixth decade":1,"100th":1,"the early hours of 14":1,"the end of November":2,"hours later":2,"Sunday ,":1,"about four years":2,"another day":2,"the 19th minute":1,"the 59th minute":3,"about":7,"24-year-old":2,"four-day":2,"more than a day":2,"nearly two years":4,"less than two years":2,"early last month":1,"Wednesday 28":1,"early June":5,"winter in":1,"Memorial Day weekend":2,"third quarter":4,"Election Day":11,"9 am":2,"1994 , the second":1,"20 minutes":4,"2003 and 2005":2,"Saturday 25":2,"the end of March":3,"Tuesday 17":3,"World Youth Day":1,"more than a decade in":1,"the end of next year":3,"1989-90":3,"the end of the 1950-53":2,"early December":2,"Friday 28":1,"mid-April":4,"the current fiscal year":1,"this October":1,"early last week":2,"later this week":2,"the final hours":2,"the last fortnight":1,"fourth year":1,"Sunday 23":1,"07 p.m.":2,"late Tuesday":4,"the end of June than":1,"the start of the week":4,"about two":1,"the second quarter Sunday":1,"March or April":1,"Memorial Day":6,"13-11":1,"Tuesday 13":3,"late June":4,"mid-July":2,"the 8th century":1,"the 89th minute":1,"April of":1,"the 14th century":4,"Election Day Nov":2,"27 years":2,"early April":3,"three-month":4,"july":1,"11 days":4,"11 am yesterday":3,"20 years":12,"31-year-old":2,"late Monday":1,"July-August":1,"the end of the week":6,"30-day":4,"late Friday":3,"1950-1953":2,"summer 's end":2,"731 days":2,"two-day":8,"8 years":2,"1950 and 2003":2,"Until":1,"the ' 60s":2,"previous decades":2,"1966 and 1976":2,"second half of":1,"midnight local time":4,"22 minutes":2,"March through the":2,"1960 and 1980":2,"early Monday":3,"the 15 years prior to":1,"this event four years ago":1,"the end of May":3,"4 minutes":2,"Sat":1,"seventh-century":1,"2 p.m.":8,"early November":6,"the coming three months":1,"1700 BC":1,"10 years":4,"the start of last year":3,"16-month":2,"1750 and 1850":2,"30 p.m.":2,"30-minute":2,"the years":4,"one day last week":1,"century":2,"late May":7,"six minutes":4,"a minute":6,"Wednesday 14":1,"170 years":6,"nearly eight-hour":2,"47 minutes":2,"Christmas Eve":4,"October 11th":1,"later Tuesday":3,"July and":1,"four years ago":5,"the first year , may":1,"5 pm":2,"last 17":1,"35 years":6,"10 p.m.":2,"and 19th century":1,"30-year-old":2,"a few days ago":1,"all of the fourth quarter":1,"41 years":2,"mid-February":2,"third":1,"10 days earlier":1,"next weekend":2,"Thursday 21":2,"the April-to-June quarter":1,"the beginning of January":2,"the second inning of Wednesday":1,"about 20 minutes":2,"Labor Day weekend":2,"the 1840s":1,"last 10 months":1,"earlier last week":1,"Monday 21":3,"the 1700s":2,"two minutes":4,"a fortnight ago":4,"11 am":2,"the beginning of August":1,"the early 1900s":1,"three quarters":4,"1993 , 1994":1,"26-17":1,"three hours":4,"three-week":2,"10.5 hours":2,"the 1820s":1,"the 50th minute":1,"4 weeks":2,"30 years":7,"24-day":4,"12 years ago":1,"the mid 1990s":2,"play last week":1,"the start of today":1,"1998-99":2,"the Day":1,"the freshly-ended quarter":1,"79-78":2,"now and Dec":2,"the end of August":5,"day in early April":2,"1933 and 2006":2,"the 17th minute":1,"a decade on Monday":1,"the year ago quarter":1,"74 minutes":2,"next month 's annual":1,"fifth weekend":1,"the beginning of June":1,"99-98":1,"past 20 years":1,"more than four years":4,"the last week of the":1,"the start of this week":3,"17 years in 2007":1,"April this year":2,"July , a week in":1,"2006 than 2005":1,"1972 , a year later":1,"2002 and 2004":2,"15 years":4,"four minutes":6,"six weeks":4,"27-17":2,"late second":2,"early on Sunday":1,"the final days of April":2,"the final quarter of the":1,"near future":1,"three days later":1,"the 2007 third quarter":1,"the early 1970s":5,"October-December quarter":1,"Friday 21":1,"a couple of months":2,"the 19th":2,"a fortnight":2,"Labor Day":7,"the beginning of the next":1,"the late 1990s":4,"this Thursday":1,"month":2,"the end of the second":1,"the last second":1,"the end of December":3,"start next year":1,"dawn that morning":2,"1368 and 1644":1,"15 days":2,"8 p.m.":8,"2002 and 2009":4,"four days":6,"early in the":1,"four months":4,"Wednesday 27":1,"59 minutes":2,"Wednesday 25":2,"July from June":1,"mid-August":3,"100 days ago":2,"43 minutes":4,"the modern day":2,"2006 and 2007":2,"the start of the decade":2,"the past century":1,"Thursday , April":1,"Tuesday 23":1,"the beginning of May":2,"days of last":1,"2003-2004":1,"more than two":2,"six week":2,"2002 , three years ago":1,"more than a quarter century":1,"three years later":1,"Tuesday , December":1,"thirty years":1,"1982 and 1986":2,"May this year":1,"37 minutes":2,"56-55":1,"1914 and 1918":2,"the end of summer":2,"1975 and 2008":2,"the following weekend":2,"12 years on September 28":1,"18-25":2,"2009 's second half":1,"20-year":2,"Sunday and Monday":2,"85 days":2,"8 a.m.":6,"Friday 13":1,"1972 and 1976":2,"10-month":2,"2010 Winter":1,"next Saturday":1,"/ 20":1,"six-hour":2,"the upcoming quarter":1,"April and the end of":2,"dawn Sunday":2,"49 years":2,"Sunday 29":1,"the financial year":1,"January last":1,"June next year":1,"the early hours of the":1,"more than two weeks":2,"the four weeks last fall":1,"the year 's end":2,"last 15 years":1,"next Tuesday":2,"2 years from":1,"last five days":1,"several hours":3,"five decades":2,"1991 , the year":1,"St":1,"January of this year":2,"later Sunday":1,"the century":1,"the next summer 's Summer":2,"5 victory":2,"eight years ago":3,"the past decades":1,"33 minutes":4,"1969 and 2000":2,"the past now":2,"less than three months on":1,"the past fortnight":1,"Father 's Day":1,"December of last year":1,"17 years":4,"the final quarter of this":1,"one":5,"January 24th":1,"5 years":2,"the month , August":1,"this Fall":1,"Fall":2,"15-15":1,"early on":2,"one week":2,"Valentine 's":1,"26 minutes":4,"next four decades":1,"past two":1,"the following month":1,"the 1600s":2,"nearly midnight":2,"end of the summer":1,"nine":4,"the 20th minute":1,"the fiscal year starting April":1,"the final 10 seconds Friday":1,"hours of Wednesday":1,"touring":2,"FRiday":1,"the third quarter before":1,"the next morning":1,"7 pm":2,"the first quarter of the":1,"several hundred years ago":1,"the 1900s":2,"the start of last summer":1,"Friday 26":1,"10-day":4,"1993 to 1998":1,"next March":3,"the 67th minute":1,"Monday 14":1,"new":2,"16 days":2,"September last":1,"October , last":1,"the first quarter of next":2,"the current quarter":1,"the start of January":1,"more than 15 years in":2,"the same month last year":2,"the 1st":1,"turning violent four days later":2,"years of the":1,"76 minutes":2,"the first week of March":1,"24-point second quarter":1,"late in the third":1,"early February last year":1,"eighth year":2,"the last hour":1,"SAT":1,"1967 Six Day War":1,"one hour":2,"the middle of":1,"Current":1,"9 p.m.":2,"2006 and 2009":2,"'":4,"and 59th minutes":1,"the past half century":1,"least a year":1,"10 days":8,"14th weekend":1,"eight months":2,"6 pm":2,"midday":2,"8 am":6,"the last days":1,"nine hours a":2,"first quarter":2,"Six-Day":2,"14th year":1,"tomorrow night":1,"the final 80 seconds on":1,"the first nine months this":1,"1979-1981":1,"This week":1,"the early hours of 25":1,"hours earlier":2,"311 minutes":2,"February and the beginning of":2,"now and Feb":2,"18 months ago":2,"last 16":2,"the first five months of":1,"the second before":1,"1969 before":2,"second quarter":3,"the first 11 months of":1,"January-August":1,"sixth":1,"'s midnight":2,"the last week before":1,"Mar last week":1,"the first three quarters of":1,"late on Friday":1,"Weekend":1,"1999-2004":1,"the early hours":2,"two days earlier":1,"the late 19th-century":1,"the third quarter of the":3,"defense minister two years":2,"2007s":1,"the 13th-century":1,"September from August":1,"the week before":1,"last January":3,"late Sunday":1,"the 20th":1,"the new millennium":1,"1975-90":2,"July 4 holiday":2,"8 p.m. and midnight":2,"the 35th minute":2,"the 75th minute":1,"the 5th century":2,"the end of February":4,"the start of spring":1,"28-month":2,"morning mist":1,"7 am":2,"last seven years":1,"the third quarter 34-15":1,"Wednesday 20":2,"1980 and 2000":2,"Friday 30":1,"mid-May":3,"Mar":2,"august":1,"the 10th century B.C.":1,"the second day of the":1,"this race two years ago":1,"the 72nd minute":1,"29 in":1,"nearly two-month":2,"more than two days":2,"the last several days":1,"Saturday 13":1,"2007 and 2009":4,"00 am":2,"two summers ago":1,"a century on":1,"following Monday":1,"32-23":1,"Wednesday 18":2,"Friday , Feb":1,"next 15 years":1,"2 a.m.":4,"the previous night":1,"Sky today":1,"Sunday 17":1,"2001 and 2006":2,"seconds of the":1,"the end of the financial":4,"last 12 months":1,"Thursday December":1,"the 15th minute":1,"July-September period from the":1,"Mother 's":1,"the first years of the":2,"nearly 12 years":2,"the month of December":1,"nine minutes":2,"more than an hour":2,"the first pitch":2,"the turn of the century":2,"nearly a":2,"Wednesday November":1,"July-September quarter":1,"this minute now":1,"last 30 years":2,"mid-May this year":2,"1990 and 2005":4,"Lords 10 years ago":1,"Fertility":1,"the Second":2,"2000 and 2016":2,"June 2004 now":1,"24 to 168 hours":2,"her first birthday":2,"55.8 million":1,"more than 60 years":2,"a month yesterday":1,"1964 and 1967":2,"July through the end of":1,"second day":1,"six to 18 months":2,"yesterday 's second":1,"1976-77":1,"60 years Monday":1,"the previous 12-month":1,"1940 before":1,"the mid-19th century":1,"the start of the fourth":2,"September , the month":1,"the third":3,"92-90":1,"July last year":2,"four days earlier":1,"1999 and 2002":2,"the 1800s":1,"the 58th minute":1,"1994 -":1,"nearly six years":2,"last 20 years":1,"five-month":2,"past 19 years":1,"the coming three years":1,"Day":4,"VE Day":2,"14th century":1,"five-day":2,"the middle of last week":1,"this Christmas":1,"the 63rd minute":1,"the previous day":1,"Thursday , Nov":1,"least a year ago":1,"Katrina four years ago":2,"Tuesday 26":2,"this week following":1,"the first week of the":1,"2005 and 2020":2,"taking the first two":2,"Maundy Thursday":1,"Thursday 25":2,"the 14th minute":2,"years in October":1,"2006 and 2008":2,"Friday 29":1,"couple of":2,"January last year":1,"21-year":2,"about 40 minutes":2,"the second quarter of next":1,"1555 and 1605":2,"60 years":3,"the end of October":2,"24 years ago":1,"seven minutes":2,"last quarter":1,"Friday and Saturday":2,"the following February":1,"Sunday 15":1,",":1,"13 days ago":1,"now and next Wednesday":2,"the 33rd minute":1,"last gasp":1,"12 p.m.":2,"15 minutes":2,"hour":2,"six-week":2,"seven years ago":1,"a year later":1,"two seconds":2,"the 11th hour":1,"57-year":2,"3 pm yesterday":1,"the German-American quarter":1,"1954 , and seven years":1,"the last several months":1,"the mid-1400s":1,"last year , this":1,"12-years-old":2,"15th anniversary":1,"the new":1,"10,000 years":2,"about an hour":3,"14 months":2,"12 months ago":1,"New Year 's Day":1,"Novermber":1,"the last minute of the":1,"Thursday November":1,"the final month":2,"nearly a year":2,"Wednesday 's eight-hour":2,"Thursday 22":1,"five days last":1,"May from a year earlier":1,"1961 and 1980":2,"the whole year":2,"Saturday 14":1,"82-year-old":2,"4 am the next morning":1,"less":3,"early last year":2,"Thursday 13":1,"the third quarter this year":1,"the 55th minute":2,"the last fiscal year":1,"Tuesday 20":2,"11 minutes":2,"April earlier":1,"seventh decade":1,"the seventeenth minute of the":1,"the second half of last":1,"the end of the half":2,"last 20":1,"39 years":2,"the coming month":1,"the same day":2,"last 10 years":2,"seven weeks ago":1,"6 am":1,"the second quarter of fiscal":1,"2004 before":1,"97-84":2,"11-year-old":2,"the 13th minute":1,"and":1,"Monday 18":1,"SATS":1,"Tuesday March":1,"December next year":1,"515 B.C.":1,"Stadium exactly three years":1,"the second half of":2,"the first three":2,"1939 and 1945":2,"2001 and 2007":2,"about three":2,"nearly two weeks":2,"the ninth year of this":1,"last 31":1,"the 44th minute":1,"momentous night":1,"beginning Sunday":1,"more than thirty years":1,"2003 and":1,"past two decades":1,"1968 to":1,"the 2006 Winter":2,"88th minute":1,"ten days ago":1,"September 14 and 18":2,"eight days":2,"5 p.m. local time":2,"16 months":2,"1 month":2,"August and September":2,"Good Friday":1,"July and October last year":2,"the beginning of December":3,"17th birthday":2,"the end of today":2,"dawn Monday":2,"1977 and 1982":2,"the 1870s":1,"last 60 minutes":1,"1996 and 2001":1,"15 months":4,"45 years":2,"the start of the month":2,"evening years":1,"30 a.m.":2,"fourth quarters":1,"week in December":1,"' 80s":1,"Tuesday August 11th":1,"28 years":2,"40 minutes":2,"five-week":2,"the first Friday":1,"second and":1,"46 years":2,"1996 and 2004":2,"tomorrow evening":1,"2nd year":1,"Masters later this":1,"their fourth birthday":2,"Falls":1,"Friday 25":1,"fourth weekend":1,"two to three weeks":2,"this month 's one-day":1,"Monday 15":1,"fall in":2,"toward":1,"Columbus Day weekend":2,"the summer of":1,"October This Year":1,"1976 before":2,"Thursdays":1,"the first half Saturday":1,"some three":1,"2004 and 2007":2,"May and early July":2,"dying minutes of the":1,"2007 , the last year":1,"Thursday 18":1,"3 days":2,"the half hour":2,"six months for 18":1,"Monday 20":2,"more than two hours":2,"the second day":1,"late on":1,"the Century":1,"46th year":1,"August this year":1,"March next year":1,"the 89th minute Sunday":1,"the 49th minute":1,"the fourth week":1,"the Fourth of July":2,"19th":2,"2001 now":1,"the fifth minute":1,"the first three months":1,"November 11th":1,"earlier this summer":1,"the start of this decade":1,"Six weeks":2,"about seventy years":2,"least two weeks":1,"19 years":2,"the start of June":2,"the next several days":1,"early days":2,"13th century":1,"end of the 1975-90":2,"the current financial year":1,"the new century 's first":1,"1998-2008":1,"custody 11 days ago":1,"Last":1,"tomorrow morning":1,"the third day":1,"about 9.10 pm yesterday":1,"the last years":1,"the seventh minute":2,"2017 / 18 to 2019":2,"10th inning":1,"the decisive second":1,"late on Wednesday":1,"past 24 hours of":1,"Open 12 months":1,"Martin":1,"the next several years":1,"1998 and 2004":2,"late July last year":2,"Friday lunchtime":1,"first days":1,"PRESENT":1,"20 seconds":2,"15th-century":1,"dawn Saturday":2,"right":2,"a month ago":1,"fiscal year":1,"6 month":2,"18 to 21 years old":2,"room 20 years":1,"Q3 of 2009":1,"Days":1,"last 14":1,"January before":1,"January 12 last":1,"1997 and 2005":2,"this Sunday":1,"October last":2,"three-hour":2,"early April last year":1,"Friday 31":1,"the final year":2,"past the hour":1,"the first week":1}